<?xml version="1.0" encoding="UTF-8" ?>
<!DOCTYPE mapper
PUBLIC "-//mybatis.org//DTD Mapper 3.0//EN"
"http://mybatis.org/dtd/mybatis-3-mapper.dtd">
<mapper namespace="com.ureca.person.model.dao.PersonDAO">
 
  <insert id="insert" parameterType="Person">
     insert into person (name,age,job) values (#{name},#{age},#{job})
  </insert>
  
  <update id="update" parameterType="person">
     update person set age=#{age}, job=#{job} where no=#{no}
  </update>
  
  <delete id="delete" parameterType="int">
     delete from person where no=#{no}
  </delete>
  
  <select id="select" parameterType="int" 
          resultType="Person">
     select no,name,age,job from person where no=#{no}
  </select>
  
  <select id="selectAll" resultType="Person">
     select no,name,age,job from person order by no desc
  </select>

</mapper>











